spatial_detrend/__init__.py
spatial_detrend/methods/__init__.py
spatial_detrend/methods/util.py
spatial_detrend/methods/simulate/__init__.py
spatial_detrend/methods/simulate/sim_signal.py
spatial_detrend/methods/solve/__init__.py
spatial_detrend/methods/solve/solver.py
spatial_detrend/methods/solve/solver_weights.py
spatial_detrend/preproc/__init__.py
spatial_detrend/preproc/grid_data.py
spatial_detrend/preproc/kepler_util.py
spatial_detrend/preproc/preprocess_data.py
spatial_detrend-0.1.0.dist-info/METADATA
spatial_detrend-0.1.0.dist-info/WHEEL
spatial_detrend-0.1.0.dist-info/top_level.txt
spatial_detrend-0.1.0.dist-info/RECORD
