Metadata-Version: 2.1
Name: spatial-detrend
Version: 0.1.0
Summary: A Python library to mitigate spatially-correlated systematic noise in Kepler light curves
Home-page: https://github.com/xiaziyna/spatial-detrend
Author: Jamila Taaki
Author-email: xiaziyna@gmail.com
License: UNKNOWN
Platform: UNKNOWN
Classifier: Development Status :: 3 - Alpha
Classifier: Intended Audience :: Science/Research
Classifier: License :: OSI Approved :: MIT License
Classifier: Programming Language :: Python :: 3
Classifier: Programming Language :: Python :: 3.6
Classifier: Programming Language :: Python :: 3.7
Classifier: Programming Language :: Python :: 3.8
Classifier: Programming Language :: Python :: 3.9
Requires-Dist: numpy
Requires-Dist: scipy
Requires-Dist: sklearn
Requires-Dist: astropy
